README.rst
setup.py
svgimgutils.py
svgimgutils.egg-info/PKG-INFO
svgimgutils.egg-info/SOURCES.txt
svgimgutils.egg-info/dependency_links.txt
svgimgutils.egg-info/requires.txt
svgimgutils.egg-info/top_level.txt