Metadata-Version: 1.0
Name: svgimgutils
Version: 0.1.0
Summary: A lightweight Python SVG parser that focuses on correctly layering SVG images
Home-page: https://github.com/Amirh24/SVG-Image-Utils.git
Author: A. Hagafny
Author-email: amirh18@gmail.com
License: MIT
Platform: UNKNOWN
